Metadata-Version: 2.1
Name: python-screen
Version: 1.0.3
Summary: A simple python wrapper for GNU Screen
Home-page: https://gitlab.com/jvadair/pyscreen
Author: jvadair
Author-email: dev@jvadair.com
License: Apache 2.0
Platform: UNKNOWN
